nimbus/__init__.py
nimbus/__main__.py
nimbus/pipeline.py
nimbus/poes.py
nimbus/samples.py
nimbus/sinks/__init__.py
nimbus/sinks/audio.py
nimbus/sinks/console.py
nimbus/sinks/image.py
nimbus/sinks/iq.py
nimbus/sinks/sdl.py
nimbus/sinks/wave.py
nimbus/sources/__init__.py
nimbus/sources/image.py
nimbus/sources/iq.py
nimbus/sources/random.py
nimbus/sources/sdr.py
nimbus/sources/wave.py
nimbus/transformers/__init__.py
nimbus/transformers/aptsync.py
nimbus/transformers/caster.py
nimbus/transformers/fmdemod.py
nimbus/transformers/gain.py
nimbus/transformers/hilbert.py
nimbus/transformers/resample.py
nimbus/transformers/tee.py
wxnimbus-0.1.1.dist-info/entry_points.txt
wxnimbus-0.1.1.dist-info/LICENSE
wxnimbus-0.1.1.dist-info/WHEEL
wxnimbus-0.1.1.dist-info/METADATA
wxnimbus-0.1.1.dist-info/RECORD
