Metadata-Version: 2.1
Name: wxnimbus
Version: 0.1.1
Summary: Nimbus is an open-source library and framework for real-time reading and decoding of data signals from NOAA polar satellites.
Home-page: https://github.com/Quinticx/nimbus
License: GPL-3.0-only
Author: Brianna Witherell
Requires-Python: >=3.8,<3.11
Classifier: License :: OSI Approved :: GNU General Public License v3 (GPLv3)
Classifier: Programming Language :: Python :: 3
Classifier: Programming Language :: Python :: 3.10
Classifier: Programming Language :: Python :: 3.8
Classifier: Programming Language :: Python :: 3.9
Requires-Dist: Pillow (>=9.0.1,<10.0.0)
Requires-Dist: PyAudio (>=0.2.11,<0.3.0)
Requires-Dist: PySDL2 (>=0.9.11,<0.10.0)
Requires-Dist: numpy (>=1.22.3,<2.0.0)
Requires-Dist: pyrtlsdr (>=0.2.92,<0.3.0)
Requires-Dist: scipy (>=1.8.0,<2.0.0)
Project-URL: Repository, https://github.com/Quinticx/nimbus
